Metadata-Version: 2.1
Name: cx_economics
Version: 1.0.0
Summary: Analyze CX economics using NPS and revenue data.
Home-page: 
Author: Veera Balakrishnan
Author-email: mail2veerads@gmail.com
License: MIT
Classifier: Programming Language :: Python :: 3
Classifier: License :: OSI Approved :: MIT License
Classifier: Operating System :: OS Independent
Requires-Python: >=3.6
License-File: LICENSE.txt
